[{"@odata.etag":"","ItemInternalId":"f45236bd-0e21-44f5-b215-55b1b9b49b8a","Wine":"Hippolyte Sancerre ","Varietal":"Sauvignon Blanc","Year":"2023","Bottles":"1"},{"@odata.etag":"","ItemInternalId":"e90011c3-7798-4132-b7e5-03e4dbe39a5e","Wine":"Racines Pinot Noir ","Varietal":"Pinot Noir","Year":"2020","Bottles":"0"},{"@odata.etag":"","ItemInternalId":"a08d4868-d003-49e4-a779-02109ef5c5be","Wine":"Cade Sauv Blanc ","Varietal":"Sauvignon Blanc","Year":"2022","Bottles":"1"},{"@odata.etag":"","ItemInternalId":"87033117-ba3e-441b-970e-e24f5bab1dc1","Wine":"","Varietal":"","Year":"","Bottles":""},{"@odata.etag":"","ItemInternalId":"940332b3-f1da-4031-b8a0-092f47653d8d","Wine":"Resa Pinot Noir ","Varietal":"Pinot Noir","Year":"2019","Bottles":"2"},{"@odata.etag":"","ItemInternalId":"0829e8fd-c191-45df-999c-b9e139a231bf","Wine":"La Spinetta Timarosso ","Varietal":"Nebbiolo","Year":"2023","Bottles":"2"},{"@odata.etag":"","ItemInternalId":"006f1684-f211-44e9-90d3-818500a072b4","Wine":"Perinet Porirat ","Varietal":"Red Blend","Year":"2017","Bottles":"1"},{"@odata.etag":"","ItemInternalId":"84180d92-bd3f-49b7-819d-a29bda7e72ed","Wine":"Alpha Omega Red Blend ","Varietal":"Red Blend","Year":"2021","Bottles":"1"},{"@odata.etag":"","ItemInternalId":"1c1ac642-b506-48d3-be33-4d3ac31fdaf1","Wine":"Ciguliti Barbaresco ","Varietal":"Nebbiolo","Year":"2021","Bottles":"0"},{"@odata.etag":"","ItemInternalId":"ea6c4862-6e00-4418-9155-75de4f54b6d1","Wine":"Massolino Barolo ","Varietal":"Nebbiolo","Year":"2019","Bottles":"0"},{"@odata.etag":"","ItemInternalId":"8da27ef5-3ee4-4ae7-9bfe-95838fefa853","Wine":"Tolosa Chardonnay ","Varietal":"Chardonnay","Year":"2019","Bottles":"3"}]