[{"@odata.etag":"","ItemInternalId":"217351ca-8ccf-433f-a5a3-3fecf3c5d142","Wine":"Bireler Rose ","Varietal":"Rose","Year":"2022","Bottles":"3"},{"@odata.etag":"","ItemInternalId":"27038e7a-69d1-4394-a082-0ae3f7e187fc","Wine":"Fontsainte Rose ","Varietal":"Rose","Year":"2022","Bottles":"1"},{"@odata.etag":"","ItemInternalId":"c4d81ed2-1bb5-4ff0-b2a8-a39a96b6fefd","Wine":"Emmolos","Varietal":"Sauvignon Blanc","Year":"2023","Bottles":"11"},{"@odata.etag":"","ItemInternalId":"7f04e5b8-91d1-4732-9faa-5f8888088133","Wine":"Duckhorn Merlot ","Varietal":"Merlot","Year":"2022","Bottles":"3"},{"@odata.etag":"","ItemInternalId":"77bb3143-d2d7-4a53-854a-c3e8b8446e57","Wine":"Beringer ","Varietal":"Cabernet Sauvignon","Year":"2020","Bottles":"2"},{"@odata.etag":"","ItemInternalId":"e96b8c8e-7760-4247-9dbd-a23be26be04e","Wine":"Marchesi di barolo","Varietal":"Nebbiolo","Year":"2019","Bottles":"5"},{"@odata.etag":"","ItemInternalId":"2bca6643-157a-4692-af03-16a1019ea1fe","Wine":"DeLille Sauv Blanc ","Varietal":"Sauvignon Blanc","Year":"2022","Bottles":"0"},{"@odata.etag":"","ItemInternalId":"222ce286-a5f8-4375-b07a-5683c64e0589","Wine":"Robert Craig","Varietal":"Red Blend","Year":"2020","Bottles":"0"},{"@odata.etag":"","ItemInternalId":"a70a40e6-6b1f-4669-9c53-801daa836e72","Wine":"Hartford Court","Varietal":"Pinot Noir","Year":"2021","Bottles":"2"},{"@odata.etag":"","ItemInternalId":"92458df0-fe6e-4a69-a2fc-a398ddcab4fc","Wine":"Lanzaga ","Varietal":"Tempranillo","Year":"2019","Bottles":"4"},{"@odata.etag":"","ItemInternalId":"e0ae7a58-289f-47d2-8b5c-ab6489fe2551","Wine":"Nolina","Varietal":"","Year":"","Bottles":"3"},{"@odata.etag":"","ItemInternalId":"a62083d9-d410-4b93-84dd-d3895d5bc914","Wine":"Crozes Hermitage MAison","Varietal":"Syrah","Year":"2021","Bottles":"1"},{"@odata.etag":"","ItemInternalId":"fafc64ab-3817-487c-af6b-8ff23a9d5233","Wine":"La Grenoiulle Roygantre","Varietal":"Rose","Year":"2022","Bottles":"10"},{"@odata.etag":"","ItemInternalId":"d4def719-69d9-43c9-9e47-484cba8e820c","Wine":"","Varietal":"","Year":"","Bottles":""},{"@odata.etag":"","ItemInternalId":"c37ad3ca-4000-4eaf-9c43-ffde96a48bbf","Wine":"","Varietal":"","Year":"","Bottles":""}]