[{"@odata.etag":"","ItemInternalId":"3ea6475a-b964-4c87-af83-bed16f11528b","Wine":"Schramsberg","Varietal":"Chardonnay","Year":"","Bottles":"2"},{"@odata.etag":"","ItemInternalId":"f2e67502-d034-4a08-8182-c58a1c08bfce","Wine":"Papillon ","Varietal":"Red Blend","Year":"","Bottles":"2"},{"@odata.etag":"","ItemInternalId":"ab4d0d04-6e98-4823-b858-cee38054ce12","Wine":"Cascina di Cornia ","Varietal":"Sangiovese","Year":"","Bottles":"1"},{"@odata.etag":"","ItemInternalId":"d58595a1-2d4c-44e0-abf6-06f3c082092b","Wine":"Zena Crown ","Varietal":"Pinot Noir","Year":"","Bottles":"3"},{"@odata.etag":"","ItemInternalId":"f3b7509d-0b93-4217-8dd6-7e998f697346","Wine":"Palazzo Brunello di Montalcino","Varietal":"Brunello","Year":"","Bottles":"1"}]