[{"@odata.etag":"","ItemInternalId":"c1cdacf8-536b-4903-a8f8-696f258e9fef","Wine":"Merry Edwards","Varietal":"Sauvignon Blanc","Year":"","Bottles":"2"},{"@odata.etag":"","ItemInternalId":"4f8c5d8d-cc71-4125-80df-325deaa5c189","Wine":"Melville","Varietal":"Pinot Noir","Year":"","Bottles":"1"},{"@odata.etag":"","ItemInternalId":"5c9a8120-6357-40d4-811e-19a6def82670","Wine":"Ireland","Varietal":"Pinot Noir","Year":"","Bottles":"2"},{"@odata.etag":"","ItemInternalId":"19943f57-586e-4172-861a-1ff4bf9b9adb","Wine":"Miner","Varietal":"Sauvignon Blanc","Year":"","Bottles":"2"}]