[{"@odata.etag":"","ItemInternalId":"cea63268-f3ce-4f94-8164-0c32afb21af9","Wine":"Sea Smoke","Varietal":"Chardonnay","Year":"2021","Bottles":"2"},{"@odata.etag":"","ItemInternalId":"1ca05647-d479-4eb5-922a-ebfa3b1d9384","Wine":"Sea Smoke","Varietal":"Pinot Noir","Year":"2018","Bottles":"1"},{"@odata.etag":"","ItemInternalId":"3577c80b-81f3-46ba-a29b-81cfd9aaa6c0","Wine":"Nicolas Jay","Varietal":"Pinot Noir","Year":"2019","Bottles":"1"},{"@odata.etag":"","ItemInternalId":"bd7b179f-a4e1-4c39-8ce3-341ac530e11b","Wine":"Fontanabianca","Varietal":"Arneis","Year":"2022","Bottles":"1"},{"@odata.etag":"","ItemInternalId":"b7ccc932-e441-4746-a936-fcf5a0ac6ef8","Wine":"Chandon","Varietal":"","Year":"No year","Bottles":"2"},{"@odata.etag":"","ItemInternalId":"49707a7b-b8a7-4797-9970-85fb7c25a28c","Wine":"Roy Estate ","Varietal":"Cabernet Sauvignon","Year":"2014","Bottles":"1"},{"@odata.etag":"","ItemInternalId":"095aa68a-e8a9-4790-9a01-f7f0e8160d4e","Wine":"Ogier Cote Rotie","Varietal":"Syrah","Year":"","Bottles":"1"},{"@odata.etag":"","ItemInternalId":"6e2445a7-2955-4db2-988b-3f7566c009fc","Wine":"Flowers","Varietal":"Chardonnay","Year":"2021","Bottles":"2"},{"@odata.etag":"","ItemInternalId":"9722be26-f60a-43e5-8714-073a301eaf30","Wine":"Legress","Varietal":"Champagne","Year":"2017","Bottles":"2"},{"@odata.etag":"","ItemInternalId":"3fa9b1b1-7ec6-49a3-b937-28fe7acfdd06","Wine":"Fontanabianca","Varietal":"Arneis","Year":"2022","Bottles":"3"},{"@odata.etag":"","ItemInternalId":"a2d843f5-bcf1-470f-83e0-15a707185523","Wine":"Domaine Weinbach","Varietal":"Riesling","Year":"2022","Bottles":"3"}]