[{"@odata.etag":"","ItemInternalId":"43a33b38-2b61-4376-9758-e2fcfbbd7d5a","Wine":"Far Niente Dolce ","Varietal":"White Blend","Year":"2016","Bottles":"2"},{"@odata.etag":"","ItemInternalId":"27b33ef6-cd29-4ece-994a-fcd17bb41710","Wine":"Peter Michael Cabernet ","Varietal":"Cabernet Sauvignon","Year":"2020","Bottles":"1"},{"@odata.etag":"","ItemInternalId":"a336b71c-e0f2-4666-90f3-5c947df85736","Wine":"Smokescreen Cabernet ","Varietal":"Cabernet Sauvignon","Year":"2016","Bottles":"1"},{"@odata.etag":"","ItemInternalId":"3921c789-3c1a-486a-8e3e-a188ee63fdce","Wine":"Trefethen Cabernet ","Varietal":"Cabernet Sauvignon","Year":"2020","Bottles":"1"},{"@odata.etag":"","ItemInternalId":"294741ea-b84a-46b2-86f4-91b789b1de19","Wine":"Raen Pinot Noir ","Varietal":"Pinot Noir","Year":"2021","Bottles":"1"}]