[{"@odata.etag":"","ItemInternalId":"923aec84-ca1a-4e74-824b-d6a7d0a6f283","Wine":"Argyle Brut Rose ","Varietal":"Rose","Year":"NV","Bottles":"1"},{"@odata.etag":"","ItemInternalId":"88e8895a-65cd-4d93-a4a9-e990da962f29","Wine":"Pine Ridge Cabernet ","Varietal":"Cabernet Sauvignon","Year":"2022","Bottles":"1"},{"@odata.etag":"","ItemInternalId":"7d2c3f7c-c6cc-4054-acb2-8dd71e2809d2","Wine":"Denner Syrah ","Varietal":"Syrah","Year":"2021","Bottles":"1"},{"@odata.etag":"","ItemInternalId":"833e08e4-5040-4560-aa7f-4fffd4e2c447","Wine":"","Varietal":"","Year":"","Bottles":""},{"@odata.etag":"","ItemInternalId":"7985d65b-3f93-4f76-aac3-753d8f06fed2","Wine":"Cristom Pinot Noir ","Varietal":"Pinot Noir","Year":"2022","Bottles":"1"},{"@odata.etag":"","ItemInternalId":"1487bfcd-61d2-4814-bf0d-816ce2178310","Wine":"Roland Lavantureux Chablis ","Varietal":"Chablis","Year":"2021","Bottles":"1"},{"@odata.etag":"","ItemInternalId":"9fdf7b20-9fc3-461e-9502-b554c024c694","Wine":"Emercy Red Blend ","Varietal":"Red Blend","Year":"2019","Bottles":"1"},{"@odata.etag":"","ItemInternalId":"994b79cd-9067-4309-bac9-fe57b610ffd2","Wine":"Ch. Gloria ","Varietal":"Red Blend","Year":"2019","Bottles":"1"},{"@odata.etag":"","ItemInternalId":"35822a04-f88f-42b0-b704-5d862a2ee4c6","Wine":"Occidental Pinot Noir ","Varietal":"Pinot Noir","Year":"2022","Bottles":"0"},{"@odata.etag":"","ItemInternalId":"e6e39f30-02f0-4e5f-ad14-b6cc65db8fd3","Wine":"El Enemigo ","Varietal":"Malbec","Year":"2021","Bottles":"1"},{"@odata.etag":"","ItemInternalId":"dba06513-4575-4fe2-a65f-48149aa72a33","Wine":"Catena Alta","Varietal":"Cabernet","Year":"2021","Bottles":"1"}]