[{"@odata.etag":"","ItemInternalId":"1eff6a07-68f5-4d94-9a5f-16cfc9d62dfd","Wine":"Perinet Pirorat ","Varietal":"Grenache","Year":"","Bottles":"1"},{"@odata.etag":"","ItemInternalId":"a68fc50f-5fc2-4b4c-bfe3-aa558c4abe11","Wine":"Cakebread Chardonnay ","Varietal":"Chardonnay","Year":"","Bottles":"0"},{"@odata.etag":"","ItemInternalId":"835d44b0-a0b0-42bf-b3ab-4a3356127de6","Wine":"Pine Ridge Cab ","Varietal":"Cabernet Sauvignon","Year":"","Bottles":"0"},{"@odata.etag":"","ItemInternalId":"c6d7f319-21f0-4b50-8222-01f49f3e5102","Wine":"Hundred Suns Gamay Noir ","Varietal":"Gamay","Year":"","Bottles":"0"},{"@odata.etag":"","ItemInternalId":"11a0d934-06e6-4cd0-a10b-a8df28f71f0a","Wine":"Hippolyte Sancerre","Varietal":"Sauvignon Blanc","Year":"","Bottles":"1"},{"@odata.etag":"","ItemInternalId":"9d922647-0c86-4097-b9d3-c4d4cbadcb21","Wine":"Tolosa Chardonnay ","Varietal":"Chardonnay","Year":"","Bottles":"1"},{"@odata.etag":"","ItemInternalId":"2265a305-c413-4210-a3bc-c1a070d05771","Wine":"Ch Moulin Tricot ","Varietal":"Bordeaux (Red)","Year":"","Bottles":"0"},{"@odata.etag":"","ItemInternalId":"76b920ab-ee06-4272-9f7b-a3cdeadf0d04","Wine":"Ch. Giscours ","Varietal":"Sauvignon Blanc","Year":"","Bottles":"1"},{"@odata.etag":"","ItemInternalId":"08da450b-3c76-4a16-a2c1-e89166a3b39d","Wine":"Spring Valley Cab ","Varietal":"","Year":"","Bottles":"0"},{"@odata.etag":"","ItemInternalId":"77e36838-b299-428e-83d2-0f6e4e9b92d1","Wine":"Simi Cab ","Varietal":"Cabernet Sauvignon","Year":"","Bottles":"1"},{"@odata.etag":"","ItemInternalId":"a68c5b9d-27b0-4d6c-97c7-6d64a5895765","Wine":"Fontabianca Arneis","Varietal":"Arneis","Year":"","Bottles":"1"},{"@odata.etag":"","ItemInternalId":"25b9d510-c458-4dd3-ad41-46fd9ee473d3","Wine":"Jonata Cab ","Varietal":"Cabernet Sauvignon","Year":"","Bottles":"1"},{"@odata.etag":"","ItemInternalId":"895305fa-2a46-48b6-9718-0fd2caa63148","Wine":"Decoy Chardonay ","Varietal":"Chardonnay","Year":"","Bottles":"1"},{"@odata.etag":"","ItemInternalId":"8bbba3c6-8dc7-4969-af4d-71cc3ba3a06b","Wine":"Ch. Gloria ","Varietal":"Bordeaux (Red)","Year":"","Bottles":"0"},{"@odata.etag":"","ItemInternalId":"dfa881a4-e6bb-4569-8f0a-5d539539efb7","Wine":"","Varietal":"","Year":"","Bottles":""},{"@odata.etag":"","ItemInternalId":"6ce44eca-5304-4960-b1b1-6ff5403b99ac","Wine":"Zena Crown Pinot Noir ","Varietal":"Pinot Noir","Year":"","Bottles":"2"},{"@odata.etag":"","ItemInternalId":"1b1ae110-740b-4ac3-938c-e3a5ef388565","Wine":"Occiedental Pinot Noir ","Varietal":"Pinot Noir","Year":"","Bottles":"0"},{"@odata.etag":"","ItemInternalId":"d6feb33c-439d-4077-87bc-015e9b8fa140","Wine":"Davies Cabernet ","Varietal":"Cabernet Sauvignon","Year":"","Bottles":"0"},{"@odata.etag":"","ItemInternalId":"beb3c696-db9e-439b-9f07-6f1475ff7342","Wine":"Failla Gruner Veltliner ","Varietal":"","Year":"","Bottles":"0"},{"@odata.etag":"","ItemInternalId":"de86695c-2c27-43ad-8d30-c74b102c826f","Wine":"Cristom Chardonnay ","Varietal":"","Year":"","Bottles":"0"},{"@odata.etag":"","ItemInternalId":"f2bb7251-3ea0-4dcc-bec8-106284984b30","Wine":"Cascina cornia Chianti ","Varietal":"Nebbiolo","Year":"","Bottles":"3"},{"@odata.etag":"","ItemInternalId":"ffce70f8-4513-4e00-8e7e-76dd54a635a1","Wine":"Arnot Robert Chardonnay ","Varietal":"Chardonnay","Year":"","Bottles":"3"},{"@odata.etag":"","ItemInternalId":"55fc0fc6-ba66-47f0-a957-fa49c2940fec","Wine":"Schramsberg Blanc de Blanc ","Varietal":"","Year":"","Bottles":"0"},{"@odata.etag":"","ItemInternalId":"c4a6b8cf-de9b-4452-97f0-cc77d27f5972","Wine":"Conterno Gattinara ","Varietal":"Nebbiolo","Year":"","Bottles":"1"},{"@odata.etag":"","ItemInternalId":"b92f9848-f4d9-45b0-9065-d820dc65aa85","Wine":"Palazzo Brunello di Montalcino","Varietal":"Sangiovese","Year":"","Bottles":"2"},{"@odata.etag":"","ItemInternalId":"de6897e0-4110-40dc-9958-42a93e76cf32","Wine":"Dievole Chianti ","Varietal":"Sangiovese","Year":"","Bottles":"1"},{"@odata.etag":"","ItemInternalId":"0fdcb253-01fa-4a72-a95d-cf7f47db2928","Wine":"Chimney Rock Cabernet ","Varietal":"Cabernet Sauvignon","Year":"","Bottles":"1"},{"@odata.etag":"","ItemInternalId":"f3f8f786-2625-4f45-9179-8ed106693d31","Wine":"Banfi Brunello di Montalcino ","Varietal":"Sangiovese","Year":"","Bottles":"1"},{"@odata.etag":"","ItemInternalId":"9db14eb4-0c21-4376-8fdf-45862913fbfc","Wine":"Faust Cabernet ","Varietal":"","Year":"","Bottles":"0"},{"@odata.etag":"","ItemInternalId":"ae5db72c-524f-49f0-8cbb-15ac05d32dcd","Wine":"Marchesi di Barolo Langhe ","Varietal":"","Year":"","Bottles":"0"},{"@odata.etag":"","ItemInternalId":"1759f93d-dd2c-40ba-a38f-351cb44e90e1","Wine":"Bordet Chablis ","Varietal":"","Year":"","Bottles":"0"},{"@odata.etag":"","ItemInternalId":"3f49dc3c-4de4-42ab-a59e-5ba34dbb0019","Wine":"Alpha Omega Cabernet ","Varietal":"","Year":"","Bottles":"0"},{"@odata.etag":"","ItemInternalId":"00f188b5-8c19-42b4-b1e5-31be556e841f","Wine":"Two Squared Red Blend ","Varietal":"","Year":"","Bottles":"0"},{"@odata.etag":"","ItemInternalId":"323e65ae-4099-4a9e-9902-1c140f709d22","Wine":"Guyllot Pouilly Fume ","Varietal":"","Year":"","Bottles":"0"},{"@odata.etag":"","ItemInternalId":"d6f0409b-fdd9-4635-854b-5e8cc7421f40","Wine":"Girlan Chardonnay ","Varietal":"","Year":"","Bottles":"0"},{"@odata.etag":"","ItemInternalId":"4b0fc578-def4-4622-9fa9-ad2c3575a717","Wine":"Silver Oak Alexander ","Varietal":"","Year":"","Bottles":"0"}]