[{"@odata.etag":"","ItemInternalId":"c8e6f3ad-15ef-48e6-a2e2-acaf09284a4c","Wine":"Chalk Hill Chardonnay ","Varietal":"Chardonnay","Year":"2021","Bottles":"1"},{"@odata.etag":"","ItemInternalId":"69e7b67e-b1c3-4566-ac51-9c5bbf532664","Wine":"Productiori del Barbaresco ","Varietal":"Nebbiolo","Year":"2019","Bottles":"2"},{"@odata.etag":"","ItemInternalId":"7db71bf7-5e68-4fd5-b6c4-9d57a445bfa8","Wine":"Ramey Chardonnay ","Varietal":"Chardonnay","Year":"2010","Bottles":"1"},{"@odata.etag":"","ItemInternalId":"1985f83a-172a-42e9-a62e-66415bc0ecd2","Wine":"En Route Pinot Noir ","Varietal":"Pinot Noir","Year":"2022","Bottles":"2"},{"@odata.etag":"","ItemInternalId":"550634fe-f1a5-4e59-9f39-b462998b1385","Wine":"Patz & Hall Chardonnay ","Varietal":"Chardonnay","Year":"2019","Bottles":"0"},{"@odata.etag":"","ItemInternalId":"3f7379c5-6228-4c31-82f2-38d23214eb85","Wine":"High Haven Pinot Noir ","Varietal":"Pinot Noir","Year":"2022","Bottles":"2"},{"@odata.etag":"","ItemInternalId":"031e993a-f792-4338-a0eb-5b8b985ac505","Wine":"Rowen Blend ","Varietal":"Red Blend","Year":"2018","Bottles":"2"},{"@odata.etag":"","ItemInternalId":"cbb7f8d3-bdc6-4429-b28c-da954a47d12b","Wine":"Jordan Chardonnay ","Varietal":"Chardonnay","Year":"2017","Bottles":"1"},{"@odata.etag":"","ItemInternalId":"a13939f4-9494-4fdc-b480-2c4bb25771e4","Wine":"Bravium Pinot Noir ","Varietal":"Pinot Noir","Year":"2021","Bottles":"1"},{"@odata.etag":"","ItemInternalId":"38bad3a5-c676-49d2-ae96-91ad4ec6846e","Wine":"St Come Cote du Rhone ","Varietal":"Syrah","Year":"2022","Bottles":"2"},{"@odata.etag":"","ItemInternalId":"5f601937-6aa3-4f81-bc09-4b0f37799a7b","Wine":"Mondavi Chardonnay ","Varietal":"Chardonnay","Year":"2018","Bottles":"2"},{"@odata.etag":"","ItemInternalId":"a0e6ba19-8ecb-48e9-958b-8edbff4ea0b5","Wine":"Chalk Hill Chardonnay ","Varietal":"Chardonnay","Year":"2021","Bottles":"2"}]