[{"@odata.etag":"","ItemInternalId":"8e9f1919-9431-4c55-b2a2-0f658b1bf069","Wine":"Belle Glos","Varietal":"Pinot Noir","Year":"2018","Bottles":"2"},{"@odata.etag":"","ItemInternalId":"f2368693-6f64-4733-897b-36ebe8bb8b2f","Wine":"Checkerboard","Varietal":"Cabernet Sauvignon","Year":"2018","Bottles":"2"},{"@odata.etag":"","ItemInternalId":"4dbdd1ba-c152-45db-92fb-da872b2f459e","Wine":"Favia ","Varietal":"Cabernet Sauvignon","Year":"2018","Bottles":"1"},{"@odata.etag":"","ItemInternalId":"a27745ba-4cc7-41e7-9198-c13609b60f7d","Wine":"Ciacci","Varietal":"Brunello","Year":"2022","Bottles":"2"},{"@odata.etag":"","ItemInternalId":"4f8a7efb-35f4-4835-85e8-80d0b02e000f","Wine":"Biondi Santi Rosso di Montalcino","Varietal":"Sangiovese","Year":"110","Bottles":"1"},{"@odata.etag":"","ItemInternalId":"af4eefc2-e2f7-4774-a940-dd897766c873","Wine":"Legras & Haas ","Varietal":"Champagne","Year":"2028","Bottles":"2"},{"@odata.etag":"","ItemInternalId":"c481d034-308d-48ad-9db6-9faa70117d00","Wine":"Occidedntal ","Varietal":"Pinot Noir","Year":"1874","Bottles":"2"},{"@odata.etag":"","ItemInternalId":"34cffb78-858c-4138-acf3-9d23558780d8","Wine":"Roy ","Varietal":"Cabernet Sauvignon","Year":"1996","Bottles":"4"},{"@odata.etag":"","ItemInternalId":"678aa082-d23f-4d09-bcf7-55dd06e5426a","Wine":"Domaine de la Romanée-Conti","Varietal":"Pinot Noir","Year":"1945","Bottles":"12"},{"@odata.etag":"","ItemInternalId":"b28a1494-0812-434c-b41b-6291c0344028","Wine":"Quilceda Creek","Varietal":"Cabernet Sauvignon","Year":"2023","Bottles":"1"},{"@odata.etag":"","ItemInternalId":"3444565a-ab59-4c69-a0d5-23c91fb55b52","Wine":"Quintessa ","Varietal":"Cabernet Sauvignon","Year":"2022","Bottles":"2"},{"@odata.etag":"","ItemInternalId":"6ba75ae6-2673-4fdc-bdbe-38986f869dcc","Wine":"Flowers ","Varietal":"Pinot Noir","Year":"2023","Bottles":"1"},{"@odata.etag":"","ItemInternalId":"4b1da452-5701-4234-8ed1-54cf532b330f","Wine":"Val di Suga Brunello di Montalcino","Varietal":"Sangiovese","Year":"2018","Bottles":"2"},{"@odata.etag":"","ItemInternalId":"6a6ccfa4-8b89-4e9d-bd36-a21a210c672b","Wine":"Forman Napa Valley Cabernet","Varietal":"Cabernet Sauvignon","Year":"2017","Bottles":"2"},{"@odata.etag":"","ItemInternalId":"d6ef22f8-0766-4129-9280-1fff47eb15ab","Wine":"Pieve Santa Restituta Brunello di Montalcino","Varietal":"Sangiovese","Year":"2019","Bottles":"2"},{"@odata.etag":"","ItemInternalId":"a7cc198e-15ca-44a7-aa54-1f09cfc9381d","Wine":"Peregrine Pinot Noir","Varietal":"Pinot Noir","Year":"2018","Bottles":"2"},{"@odata.etag":"","ItemInternalId":"dbeca127-c91f-40d9-9d22-28f57e7a8694","Wine":"The Pact ","Varietal":"Cabernet Sauvignon","Year":"2022","Bottles":"3"},{"@odata.etag":"","ItemInternalId":"75cee507-f280-4991-a58b-06c86c77a763","Wine":"Favia ","Varietal":"Cabernet Sauvignon","Year":"2022","Bottles":"3"},{"@odata.etag":"","ItemInternalId":"f9624521-b1a0-406d-9589-e45a5a29ff57","Wine":"Flowers Sea View Ridge ","Varietal":"Pinot Noir","Year":"2023","Bottles":"3"},{"@odata.etag":"","ItemInternalId":"4aa4a28b-ee26-418b-8b82-c3e858b0b1ed","Wine":"Sea Smoke Ten ","Varietal":"Pinot Noir","Year":"2023","Bottles":"3"},{"@odata.etag":"","ItemInternalId":"dc434937-6895-4fd3-9b47-0214b4676c35","Wine":"Sea Smoke Southing ","Varietal":"Pinot Noir","Year":"2023","Bottles":"3"},{"@odata.etag":"","ItemInternalId":"84bc7bd6-e88e-4b09-84c5-7ff1294b4ad2","Wine":"Hundred Acre 2022 Morgans way ","Varietal":"Cabernet Sauvignon","Year":"2022","Bottles":"2"},{"@odata.etag":"","ItemInternalId":"d599c298-6e11-4ac8-83f8-20933687ba6f","Wine":"Hundred Acre Wraith ","Varietal":"Cabernet Sauvignon","Year":"2022","Bottles":"1"}]