[{"@odata.etag":"","ItemInternalId":"0cdff0df-29a0-4ac2-86d4-e4b26d8eed1f","Wine":"Failla Pinot Noir ","Varietal":"Pinot Noir","Year":"2021","Bottles":"1"},{"@odata.etag":"","ItemInternalId":"ea4befb0-28d6-4e45-a53f-93688f1290a2","Wine":"En Route Pinot Noir ","Varietal":"Pinot Noir","Year":"2022","Bottles":"0"},{"@odata.etag":"","ItemInternalId":"0371e5e7-6a99-45f9-a872-f5c175fcb65d","Wine":"Saseti Brunello di Montalcino ","Varietal":"Sangiovese","Year":"2007","Bottles":"1"},{"@odata.etag":"","ItemInternalId":"a623ae6d-195a-4222-a1c5-eb877ada11ab","Wine":"Cascina Baricchi Barbaresco","Varietal":"Nebbiolo","Year":"2007","Bottles":"1"},{"@odata.etag":"","ItemInternalId":"d10e5cb5-e02e-4936-bc7e-52a444e017ff","Wine":"Cade Sauvignon Blanc ","Varietal":"Sauvignon Blanc","Year":"2022","Bottles":"0"},{"@odata.etag":"","ItemInternalId":"61b8d3d4-3a44-4ec4-9a4e-2ceceaaa29de","Wine":"Productori del Barbarersco ","Varietal":"Nebbiolo","Year":"2019","Bottles":"2"},{"@odata.etag":"","ItemInternalId":"fc4ef558-c942-4bfd-9d80-02dd216621fd","Wine":"Giacomo Grimaldi","Varietal":"Nebbiolo","Year":"2020","Bottles":"2"},{"@odata.etag":"","ItemInternalId":"f39b40d0-5058-4956-8238-f2c0b7e25958","Wine":"Scarpa Barbaresco ","Varietal":"Nebbiolo","Year":"2019","Bottles":"0"},{"@odata.etag":"","ItemInternalId":"40312341-2ae4-4925-ada9-39006165607b","Wine":"Occidental","Varietal":"Pinot Noir","Year":"2023","Bottles":"6"}]