[{"@odata.etag":"","ItemInternalId":"cee3ceaa-4eed-4624-b85c-535cd9d944a2","Wine":"Ogier Cote Rotie","Varietal":"Viognier","Year":"2020","Bottles":"3"},{"@odata.etag":"","ItemInternalId":"16c19c40-2db0-450c-86ac-38a70e268ca9","Wine":"Ch. Armens ","Varietal":"Bordeaux (Red)","Year":"2019","Bottles":"0"},{"@odata.etag":"","ItemInternalId":"933b468a-d4c8-44cc-a1df-e1d8f8223021","Wine":"Dagueneau Pouilly Fume ","Varietal":"Sauvignon Blanc","Year":"2022","Bottles":"5"},{"@odata.etag":"","ItemInternalId":"c641d687-7e83-4e20-9e65-5b9cc80abb73","Wine":"Olivier Leflaive bourgogne Blanc ","Varietal":"Chablis (White Burgundy style Chardonnay)","Year":"2022","Bottles":"2"},{"@odata.etag":"","ItemInternalId":"2891f6f4-6cba-401a-a456-3216a1c3faa8","Wine":"8 years in the desert ","Varietal":"Zinfandel","Year":"","Bottles":"9"}]