[{"@odata.etag":"","ItemInternalId":"c3d8ec02-1a82-4f98-bc83-0ec4fcf76d23","Wine":"Louis Latour Volnay ","Varietal":"Pinot Noir","Year":"","Bottles":"5"},{"@odata.etag":"","ItemInternalId":"1633fbb1-1250-41da-a07d-91e135a66559","Wine":"Faiveley Mercurey ","Varietal":"Burgundy (Red Pinot Noir)","Year":"","Bottles":"3"},{"@odata.etag":"","ItemInternalId":"dd4e6a95-9c34-402b-9bde-33d989939b30","Wine":"CH. D'Issan Margaux","Varietal":"Bordeaux (Red)","Year":"","Bottles":"1"},{"@odata.etag":"","ItemInternalId":"737463a0-ecc3-4660-af2f-a3fc2618f795","Wine":"Caterwall Cabernet Sauvignon","Varietal":"","Year":"","Bottles":"0"},{"@odata.etag":"","ItemInternalId":"0ed49352-ec4d-4930-bdde-2d887aa56e69","Wine":"Eisele Sauvignon Blanc ","Varietal":"Sauvignon Blanc","Year":"","Bottles":"2"},{"@odata.etag":"","ItemInternalId":"37ed052a-8044-4b2e-ab00-8c578a6c0776","Wine":"Far Niente Cabernet Sauvignon","Varietal":"","Year":"","Bottles":"0"},{"@odata.etag":"","ItemInternalId":"abbaa18a-c82d-4c4b-be67-a67a8bce85c4","Wine":"Rochioli Sauvignon Blanc ","Varietal":"Sauvignon Blanc","Year":"","Bottles":"1"},{"@odata.etag":"","ItemInternalId":"2e832cf4-9bae-47df-926b-fb39f0d883b3","Wine":"Stephane Ogier Cote Rotie ","Varietal":"Syrah","Year":"","Bottles":"1"}]