[{"@odata.etag":"","ItemInternalId":"51ab0294-680a-4532-9c7c-7d13f327928f","Wine":"Saffredi ","Varietal":"Red Blend","Year":"2017","Bottles":"1"},{"@odata.etag":"","ItemInternalId":"e4818b80-c749-4c61-8f00-f62d67566cd6","Wine":"Buglioni Amarone","Varietal":"Red Blend","Year":"2009","Bottles":"0"},{"@odata.etag":"","ItemInternalId":"ffa0733b-3669-4e3f-bf5b-1b7a56d4a08e","Wine":"Adaptation ","Varietal":"Cabernet Sauvignon","Year":"2018","Bottles":"3"},{"@odata.etag":"","ItemInternalId":"b0865ad9-ff33-4666-85bc-a3ce3674e2d8","Wine":"Nozzole ","Varietal":"Sangiovese","Year":"2012","Bottles":"1"},{"@odata.etag":"","ItemInternalId":"269f7f47-82be-4052-9aed-4cc3a5f7cadb","Wine":"Domaine Matrot Mersault","Varietal":"White Blend","Year":"2022","Bottles":"6"},{"@odata.etag":"","ItemInternalId":"005db910-f521-46c3-a8fb-781b55ac544c","Wine":"Amista ","Varietal":"Barbera","Year":"2019","Bottles":"0"},{"@odata.etag":"","ItemInternalId":"d8594e87-8974-41bf-a296-6cf57397b98d","Wine":"Roy Estate","Varietal":"Red Blend","Year":"2018","Bottles":"6"},{"@odata.etag":"","ItemInternalId":"b88ea21e-d9f1-491a-b564-309915dc2d2f","Wine":"Luigi Baudana ","Varietal":"Nebbiolo","Year":"2020","Bottles":"1"},{"@odata.etag":"","ItemInternalId":"43736e15-c401-430a-a334-5545174d1928","Wine":"La Spinetta ","Varietal":"Timorasso","Year":"2023","Bottles":"2"},{"@odata.etag":"","ItemInternalId":"ef460f0f-12c1-4cd4-b5c5-33d1703fefe6","Wine":"Ste Michelle ","Varietal":"Chardonnay","Year":"2020","Bottles":"1"},{"@odata.etag":"","ItemInternalId":"2d62566c-fac4-412f-b9f8-bc1d105e05d1","Wine":"Ste Miochelle ","Varietal":"Cabernet Sauvignon","Year":"2020","Bottles":"0"},{"@odata.etag":"","ItemInternalId":"09c61e67-d737-41a0-a58c-8536722a6868","Wine":"Col Solare ","Varietal":"Cabernet Sauvignon","Year":"2019","Bottles":"1"},{"@odata.etag":"","ItemInternalId":"113f8530-e631-4fef-9f43-1991f706dd05","Wine":"Spring Valley ","Varietal":"Cabernet Sauvignon","Year":"2017","Bottles":"1"},{"@odata.etag":"","ItemInternalId":"3aaac171-b0d8-4ed6-a5cf-e9d05cbd6d1d","Wine":"Prunotto ","Varietal":"Cabernet Sauvignon","Year":"2019","Bottles":"0"},{"@odata.etag":"","ItemInternalId":"87e41b3b-ca3c-4450-b910-54586e22d686","Wine":"Louis Michel & Fils","Varietal":"Chardonnay","Year":"2022","Bottles":"6"},{"@odata.etag":"","ItemInternalId":"5e08d0a0-4fd8-48d7-8de3-6402bef6f3f7","Wine":"Volnay Louis Latour","Varietal":"Pinot Noir","Year":"2018","Bottles":"6"}]