[{"@odata.etag":"","ItemInternalId":"3bec2b43-64e1-48cd-9d49-2b4a17afee58","Wine":"Pine Ridge Cabernet ","Varietal":"Cabernet Sauvignon","Year":"2022","Bottles":"0"},{"@odata.etag":"","ItemInternalId":"561c08f2-2ba1-4149-bd7a-82a43f8a1090","Wine":"","Varietal":"","Year":"","Bottles":""},{"@odata.etag":"","ItemInternalId":"b1a2d86c-a666-4619-92f7-110574a39e92","Wine":"Chimney Rock Cabernet ","Varietal":"Cabernet Sauvignon","Year":"2017","Bottles":"0"},{"@odata.etag":"","ItemInternalId":"261625ce-492c-446b-80f6-16e6d7c616ef","Wine":"Spring Valley Cabernet ","Varietal":"Cabernet Sauvignon","Year":"2017","Bottles":"1"},{"@odata.etag":"","ItemInternalId":"fde3ba13-ab64-44dc-af64-05666d483596","Wine":"Hippolyte Sancerre","Varietal":"Cabernet Sauvignon","Year":"2023","Bottles":"1"},{"@odata.etag":"","ItemInternalId":"6c5b0d08-3bab-4b6f-9c4a-550a61ece97f","Wine":"Louis Martini Cabernet ","Varietal":"Cabernet Sauvignon","Year":"2019","Bottles":"1"},{"@odata.etag":"","ItemInternalId":"65ccc662-6b08-4799-b159-f467dcc4eb53","Wine":"Unity Pinot Noir ","Varietal":"Pinot Noir","Year":"2017","Bottles":"1"},{"@odata.etag":"","ItemInternalId":"6c74278b-b3e5-4bc9-84aa-75b0d913c4ef","Wine":"Booker Grenache ","Varietal":"Grenache","Year":"2019","Bottles":"1"},{"@odata.etag":"","ItemInternalId":"55917175-d26c-4984-b322-72f4f6788c0e","Wine":"Sean Miinor Pinot Noir ","Varietal":"Pinot Noir","Year":"2021","Bottles":"1"},{"@odata.etag":"","ItemInternalId":"518d144b-9014-4f57-a668-ad93cf73b657","Wine":"Dupeibble Beaujolais ","Varietal":"Gamay","Year":"2021","Bottles":"1"},{"@odata.etag":"","ItemInternalId":"5d4ae746-180c-4dbd-b817-eaae88070699","Wine":"Dievole Chianti ","Varietal":"Sangiovese","Year":"2021","Bottles":"1"},{"@odata.etag":"","ItemInternalId":"d990a604-6cd6-4982-9971-c32eb059ae64","Wine":"Racines Pinot Noir ","Varietal":"Pinot Noir","Year":"2020","Bottles":"1"},{"@odata.etag":"","ItemInternalId":"a8420801-b580-4b35-96b2-2e46000d7486","Wine":"Simi Cabernet ","Varietal":"Cabernet Sauvignon","Year":"2019","Bottles":"1"},{"@odata.etag":"","ItemInternalId":"44562257-b6d6-4c00-bf78-f9e9d192df38","Wine":"Fonsainte ","Varietal":"Red Blend","Year":"2022","Bottles":"1"},{"@odata.etag":"","ItemInternalId":"54595b1f-9023-493f-8702-1714b967c47b","Wine":"Failla Gruner Veltliner ","Varietal":"Grüner Veltliner","Year":"2021","Bottles":"1"},{"@odata.etag":"","ItemInternalId":"31992559-8ebb-472d-a22e-e088b408f5de","Wine":"Cakebread Chardonnay","Varietal":"Chardonnay","Year":"2022","Bottles":"1"},{"@odata.etag":"","ItemInternalId":"8caf2dcf-183b-4b7a-8e80-37aa14540ba8","Wine":"Scouts honor","Varietal":"Zinfandel","Year":"2022","Bottles":"1"},{"@odata.etag":"","ItemInternalId":"415a069a-7e70-4097-a746-f6a3edd6effa","Wine":"","Varietal":"","Year":"","Bottles":""}]