[{"@odata.etag":"","ItemInternalId":"4446ae6c-869e-4e41-84b4-49d229216925","Wine":"Ch. La Nerthe Chateauneuf-du-Pape","Varietal":"Grenache","Year":"2019","Bottles":"1"},{"@odata.etag":"","ItemInternalId":"75f480f9-540f-406c-b2b4-c617de9589a2","Wine":"Occidental","Varietal":"Pinot Noir","Year":"2023","Bottles":"8"},{"@odata.etag":"","ItemInternalId":"3dabfbe5-844c-4013-9e47-49f6dbf19f90","Wine":"Lioco Pinot","Varietal":"Pinot Noir","Year":"2021","Bottles":"0"},{"@odata.etag":"","ItemInternalId":"8ebb5c75-841f-42eb-b196-427c1e3e3d22","Wine":"Sangiacomo Pinot Noir ","Varietal":"Pinot Noir","Year":"2021","Bottles":"0"}]