[{"@odata.etag":"","ItemInternalId":"bb0fdbee-11bc-4514-b493-af8e18301490","Wine":"Mt. Brave","Varietal":"Cabernet Franc","Year":"2018","Bottles":"2"},{"@odata.etag":"","ItemInternalId":"839c9428-ea04-4b69-9661-8330badcf077","Wine":"Ca'Marcanda Magari","Varietal":"Red Blend","Year":"2021","Bottles":"1"},{"@odata.etag":"","ItemInternalId":"c5fd9474-db84-490d-8758-d052e78c9bf9","Wine":"Pahlmeyer","Varietal":"Chardonnay","Year":"2021","Bottles":"2"},{"@odata.etag":"","ItemInternalId":"9c00f613-5760-4091-a984-7a8bf693b0d9","Wine":"Occidental","Varietal":"Pinot Noir","Year":"2023","Bottles":"6"},{"@odata.etag":"","ItemInternalId":"82fcfdf5-188f-48cc-997f-05e4cca470c5","Wine":"Roy  - Mr. Evans","Varietal":"Red Blend","Year":"2018","Bottles":"0"},{"@odata.etag":"","ItemInternalId":"8280f7d6-2199-4209-a02a-cd61ec07b641","Wine":"Realm The Bard ","Varietal":"Red Blend","Year":"2021","Bottles":"1"},{"@odata.etag":"","ItemInternalId":"078b1508-f6bd-4f7f-8758-a5e5fcb535b0","Wine":"","Varietal":"","Year":"","Bottles":""}]