[{"@odata.etag":"","ItemInternalId":"5143fa33-4e44-402e-a3e0-4b8260169bec","Wine":"Occidental ","Varietal":"Pinot Noir","Year":"2023","Bottles":"3"},{"@odata.etag":"","ItemInternalId":"26aba7f3-b037-4dbf-98d3-122bc1a4162d","Wine":"Faust ","Varietal":"Cabernet Sauvignon","Year":"2022","Bottles":"1"},{"@odata.etag":"","ItemInternalId":"e8718130-5170-43d0-a56c-51e34089e5ff","Wine":"Sbirolo Marchesi di Barolo","Varietal":"Nebbiolo","Year":"2022","Bottles":"1"},{"@odata.etag":"","ItemInternalId":"392f63d3-c523-487e-ac17-0ab57086546f","Wine":"Sean Minor ","Varietal":"Pinot Noir","Year":"2021","Bottles":"1"},{"@odata.etag":"","ItemInternalId":"206f3602-dd9f-4bb4-bc83-425d6e7f12aa","Wine":"Renegade- Ancient Peaks ","Varietal":"Red Blend","Year":"2020","Bottles":"1"},{"@odata.etag":"","ItemInternalId":"e6ef6650-3412-406b-80e5-473a6d5514d6","Wine":"Cristom ","Varietal":"Chardonnay","Year":"2021","Bottles":"0"},{"@odata.etag":"","ItemInternalId":"cc48e980-3158-4ff1-b42a-80d821a8e4fd","Wine":"HDV ","Varietal":"Pinot Noir","Year":"2021","Bottles":"0"},{"@odata.etag":"","ItemInternalId":"afa7bbef-3f2f-4d5c-a782-f4196e1ac7be","Wine":"Dievole ","Varietal":"Sangiovese","Year":"2021","Bottles":"1"},{"@odata.etag":"","ItemInternalId":"f279a320-b128-4865-9406-b5f8d37d6af3","Wine":"Sixteen Appellations- Italics ","Varietal":"Cabernet Sauvignon","Year":"2013","Bottles":"1"}]