[{"@odata.etag":"","ItemInternalId":"9d583918-e818-4fa3-b55c-ec84facd5feb","Wine":"Belle Glos","Varietal":"Pinot Noir","Year":"","Bottles":"0"},{"@odata.etag":"","ItemInternalId":"632d9d37-4856-4318-83c6-ec279a99929e","Wine":"Occidental","Varietal":"Pinot Noir","Year":"","Bottles":"1"},{"@odata.etag":"","ItemInternalId":"35fab58f-fe75-4737-885a-4acfaa3f76ab","Wine":"Quilt","Varietal":"Cabernet Sauvignon","Year":"","Bottles":"3"},{"@odata.etag":"","ItemInternalId":"86814397-d6d6-426d-962a-bd196cfb6bfd","Wine":"Resonance","Varietal":"Pinot Noir","Year":"","Bottles":"2"}]