[{"@odata.etag":"","ItemInternalId":"973caafe-53cf-4f16-8add-5357587222dd","Wine":"Twomey","Varietal":"Pinot Noir","Year":"2022","Bottles":"7"},{"@odata.etag":"","ItemInternalId":"4264af14-34ae-4988-8f4e-116bb03a7879","Wine":"Twomey","Varietal":"Merlot","Year":"2015","Bottles":"3"},{"@odata.etag":"","ItemInternalId":"7cb47e77-93ae-4bda-bc64-d1a2afd36e30","Wine":"","Varietal":"","Year":"","Bottles":""},{"@odata.etag":"","ItemInternalId":"85ec8630-8e1d-45cd-a225-ea48fac5f92e","Wine":"","Varietal":"","Year":"","Bottles":""},{"@odata.etag":"","ItemInternalId":"a5878b0b-7b7e-4e44-a637-94c112573987","Wine":"","Varietal":"","Year":"","Bottles":""},{"@odata.etag":"","ItemInternalId":"818e4b36-1530-44cd-bd12-9cf8b5a25a3f","Wine":"","Varietal":"","Year":"","Bottles":""},{"@odata.etag":"","ItemInternalId":"f8196507-4ab7-470a-bcc5-fdbb33aed108","Wine":"","Varietal":"","Year":"","Bottles":""},{"@odata.etag":"","ItemInternalId":"d128a3f8-fd85-4482-a070-93d26dca8c49","Wine":"","Varietal":"","Year":"","Bottles":""},{"@odata.etag":"","ItemInternalId":"15fce372-c7b3-4fe7-aa2d-21e82c617aac","Wine":"","Varietal":"","Year":"","Bottles":""}]