[{"@odata.etag":"","ItemInternalId":"2dbc6722-39e2-4116-8d1e-dc79306954d9","Wine":"Cristom ","Varietal":"Chardonnay","Year":"2021","Bottles":"0"},{"@odata.etag":"","ItemInternalId":"d862c015-a968-4d36-bbf5-2f8e23518381","Wine":"Cavallotto","Varietal":"Nebbiolo","Year":"2020","Bottles":"1"},{"@odata.etag":"","ItemInternalId":"6332dddc-a082-473b-a3d9-4b04d89d89d6","Wine":"J. Davies ","Varietal":"","Year":"","Bottles":"0"},{"@odata.etag":"","ItemInternalId":"1a5123b4-83d9-4485-a22d-e2dcec7a090e","Wine":"Jax","Varietal":"Rose","Year":"2022","Bottles":"1"},{"@odata.etag":"","ItemInternalId":"f25c6fa7-8ee8-4f57-b67e-00a431d768d9","Wine":"Racines ","Varietal":"Pinot Noir","Year":"2020","Bottles":"0"},{"@odata.etag":"","ItemInternalId":"997a2262-1048-4363-879f-acccbe8e296f","Wine":"J. Davies ","Varietal":"Cabernet Sauvignon","Year":"2019","Bottles":"0"},{"@odata.etag":"","ItemInternalId":"13416d33-29b6-4178-8e42-629d1ef1115b","Wine":"Jayson Cabernet ","Varietal":"","Year":"","Bottles":"0"},{"@odata.etag":"","ItemInternalId":"355e92c6-0e8f-466f-95f1-e651ea445800","Wine":"Dom. Vauroux ","Varietal":"Chablis","Year":"2018","Bottles":"1"},{"@odata.etag":"","ItemInternalId":"2b90065f-6a5c-4950-8656-88b87d9018d8","Wine":"Ch. Gloria","Varietal":"Bordeaux (Red)","Year":"2019","Bottles":"1"},{"@odata.etag":"","ItemInternalId":"386ed4d9-0dbf-488e-acef-2aa2a3be13bc","Wine":"Hundres Suns ","Varietal":"Gamay","Year":"2023","Bottles":"0"},{"@odata.etag":"","ItemInternalId":"40c1603e-572f-4881-8476-3a19d910f483","Wine":"Senses","Varietal":"Chardonnay","Year":"2020","Bottles":"1"},{"@odata.etag":"","ItemInternalId":"a43f2c8f-c5e0-4fc0-b1cc-1a474bc58a4f","Wine":"Oubile- Booker ","Varietal":"Grenache","Year":"2019","Bottles":"0"},{"@odata.etag":"","ItemInternalId":"a6b09314-77f2-4846-9159-d5b89b53a678","Wine":"","Varietal":"","Year":"","Bottles":""},{"@odata.etag":"","ItemInternalId":"bfbaaec5-8d75-4439-b5c7-f7a8f65babd4","Wine":"Faust ","Varietal":"Cabernet Sauvignon","Year":"2022","Bottles":"1"},{"@odata.etag":"","ItemInternalId":"ef1abb9f-6740-4046-86df-ced3a1a25027","Wine":"Hippolyte Treverdy","Varietal":"Sauvignon Blanc","Year":"2023","Bottles":"1"},{"@odata.etag":"","ItemInternalId":"6788e4c7-d026-43b7-8eca-a023a58c4b4a","Wine":"Sbirolo Marchesi di Barolo ","Varietal":"Nebbiolo","Year":"2022","Bottles":"0"},{"@odata.etag":"","ItemInternalId":"7602afd3-3c8c-442a-a911-ef6beaea579a","Wine":"Mareschi di Barolo Nebbiolo ","Varietal":"","Year":"","Bottles":"0"},{"@odata.etag":"","ItemInternalId":"fa3bfd51-cc3e-420d-ac7e-de0044b946a8","Wine":"Brea Cabernet ","Varietal":"Cabernet Sauvignon","Year":"","Bottles":"2"},{"@odata.etag":"","ItemInternalId":"680a0879-ce88-4a75-ae89-5f211e583a77","Wine":"Hippolyte Sancerre ","Varietal":"","Year":"","Bottles":"0"},{"@odata.etag":"","ItemInternalId":"7dd6373f-e349-4b21-b310-3f4cc6215194","Wine":"Pahlmeyer Jayson","Varietal":"Red Blend","Year":"2021","Bottles":"1"},{"@odata.etag":"","ItemInternalId":"4317d74b-abc9-4d4b-8cc4-005bfeda99df","Wine":"Hech & Bannier Bandol ","Varietal":"Mourvèdre","Year":"2015","Bottles":"2"},{"@odata.etag":"","ItemInternalId":"cdea84ad-d075-4670-9bde-73e21fdcbcc0","Wine":"Murrieta Rioja Riserva ","Varietal":"Tempranillo","Year":"2020","Bottles":"1"},{"@odata.etag":"","ItemInternalId":"95ff61e5-f578-41f6-bed3-616a3f47208c","Wine":"Penner Ash ","Varietal":"Pinot Noir","Year":"2022","Bottles":"1"},{"@odata.etag":"","ItemInternalId":"ca8f45a9-5f8d-4c04-b554-a698e252177f","Wine":"Château de Beaucastel Châteauneuf-du-Pape","Varietal":"Grenache","Year":"2022","Bottles":"1"},{"@odata.etag":"","ItemInternalId":"4076e401-9130-4166-b90f-415628f8a0dd","Wine":"","Varietal":"","Year":"","Bottles":""},{"@odata.etag":"","ItemInternalId":"1b40006a-d9f2-441e-9e5a-2d7d966402e2","Wine":"","Varietal":"","Year":"","Bottles":""},{"@odata.etag":"","ItemInternalId":"f0ee287a-7d1c-43db-9679-01bfaec25cda","Wine":"","Varietal":"","Year":"","Bottles":""},{"@odata.etag":"","ItemInternalId":"b1188389-2206-406d-bcd1-72d49b4521e5","Wine":"","Varietal":"","Year":"","Bottles":""},{"@odata.etag":"","ItemInternalId":"03b668a6-3a1a-4a6e-aad6-8185db06f29f","Wine":"","Varietal":"","Year":"","Bottles":""},{"@odata.etag":"","ItemInternalId":"3d1d609e-b213-4495-86b2-ce7e9e89c972","Wine":"","Varietal":"","Year":"","Bottles":""}]