[{"@odata.etag":"","ItemInternalId":"487f57e8-8e94-42f1-9bc1-6d41b53f7f34","Wine":"Twomey","Varietal":"Pinot Noir","Year":"2022","Bottles":"2"},{"@odata.etag":"","ItemInternalId":"d44f540d-d011-4486-9102-7cbc1333cfd9","Wine":"Twomey","Varietal":"Merlot","Year":"2015","Bottles":"3"},{"@odata.etag":"","ItemInternalId":"ddf1fb79-c6a9-4d40-94e3-9b2442cbb6d4","Wine":"","Varietal":"","Year":"","Bottles":""},{"@odata.etag":"","ItemInternalId":"06c83225-4fe2-4c7d-ab5a-713b3fa42afb","Wine":"","Varietal":"","Year":"","Bottles":""},{"@odata.etag":"","ItemInternalId":"3ff7bdb9-714b-49c1-bf6f-e5305a1429f1","Wine":"","Varietal":"","Year":"","Bottles":""},{"@odata.etag":"","ItemInternalId":"bfb781cf-d00f-4eb4-871b-6a969c87b738","Wine":"","Varietal":"","Year":"","Bottles":""},{"@odata.etag":"","ItemInternalId":"981bb113-2168-43c3-9a7e-20805f9559f4","Wine":"","Varietal":"","Year":"","Bottles":""},{"@odata.etag":"","ItemInternalId":"48500abf-a167-4f5b-b99a-eea1b8e96534","Wine":"","Varietal":"","Year":"","Bottles":""},{"@odata.etag":"","ItemInternalId":"e681ca10-1c44-4bb2-91ed-a12f658f599b","Wine":"","Varietal":"","Year":"","Bottles":""}]